gfdl_rest/GetExchangeMessages.py
gfdl_rest/GetExchangeSnapshot.py
gfdl_rest/GetExchanges.py
gfdl_rest/GetExpiryDates.py
gfdl_rest/GetHistory.py
gfdl_rest/GetHistoryGreeks.py
gfdl_rest/GetInstrumentTypes.py
gfdl_rest/GetInstruments.py
gfdl_rest/GetInstrumentsOnSearch.py
gfdl_rest/GetLastQuote.py
gfdl_rest/GetLastQuoteArray.py
gfdl_rest/GetLastQuoteArrayOptionGreeks.py
gfdl_rest/GetLastQuoteArrayShort.py
gfdl_rest/GetLastQuoteArrayShortWithClose.py
gfdl_rest/GetLastQuoteOptionChain.py
gfdl_rest/GetLastQuoteOptionGreeks.py
gfdl_rest/GetLastQuoteOptionGreeksChain.py
gfdl_rest/GetLastQuoteShort.py
gfdl_rest/GetLastQuoteShortWithClose.py
gfdl_rest/GetLimitation.py
gfdl_rest/GetMarketMessages.py
gfdl_rest/GetOptionTypes.py
gfdl_rest/GetProducts.py
gfdl_rest/GetServerInfo.py
gfdl_rest/GetSnapshot.py
gfdl_rest/GetStrikePrices.py
gfdl_rest/GetTopGainersLosers.py
gfdl_rest/__init__.py
gfdl_rest/base_api.py
gfdl_rest-1.0.3.dist-info/METADATA
gfdl_rest-1.0.3.dist-info/WHEEL
gfdl_rest-1.0.3.dist-info/top_level.txt
gfdl_rest-1.0.3.dist-info/RECORD
