Metadata-Version: 2.1
Name: gfdl_rest
Version: 1.0.3
Summary: Beta Package to implement REST API of Global Datafeeds
Author: Global Datafeeds
Author-email: developer@globaldatafeeds.in
Classifier: Programming Language :: Python :: 3
Classifier: License :: OSI Approved :: MIT License
Classifier: Operating System :: OS Independent
Requires-Python: >=3.6
Requires-Dist: requests
